pyd_mon/__init__.py
pyd_mon/main.py
pyd_mon-0.2.0.dist-info/LICENSE
pyd_mon-0.2.0.dist-info/WHEEL
pyd_mon-0.2.0.dist-info/METADATA
pyd_mon-0.2.0.dist-info/RECORD
