Metadata-Version: 2.1
Name: pyd-mon
Version: 0.2.0
Summary: A super small package for validating and converting MongoDB ObjectId's to Pydantic models.
Home-page: https://github.com/MrTj458/pyd-mon
License: MIT
Author: Trevor Hodsdon
Requires-Python: >=3.9,<4.0
Classifier: License :: OSI Approved :: MIT License
Classifier: Programming Language :: Python :: 3
Classifier: Programming Language :: Python :: 3.9
Requires-Dist: pydantic (>=1.8.2,<2.0.0)
Requires-Dist: pymongo (>=3.12.0,<4.0.0)
Project-URL: Documentation, https://github.com/MrTj458/pyd-mon
Project-URL: Repository, https://github.com/MrTj458/pyd-mon
